gliner2/__init__.py
gliner2/api_client.py
gliner2/layers.py
gliner2/model.py
gliner2/old_trainer.py
gliner2/processor.py
gliner2/inference/__init__.py
gliner2/inference/engine.py
gliner2/training/__init__.py
gliner2/training/data.py
gliner2/training/lora.py
gliner2/training/trainer.py
gliner2-1.2.3.dist-info/licenses/LICENSE
gliner2-1.2.3.dist-info/METADATA
gliner2-1.2.3.dist-info/WHEEL
gliner2-1.2.3.dist-info/top_level.txt
gliner2-1.2.3.dist-info/RECORD
