Metadata-Version: 2.4
Name: gliner2
Version: 1.2.3
Maintainer: Urchade Zaratiana
Requires-Python: >=3.8
License-File: LICENSE
Requires-Dist: gliner
Dynamic: license-file
